[{"anonymous":false,"inputs":[{"indexed":true,"internalType":"address","name":"asset","type":"address"},{"indexed":true,"internalType":"address","name":"defaultInterestRateStrategyAddress","type":"address"}],"name":"AddedInterestRateStrategyAddress","type":"event"},{"anonymous":false,"inputs":[{"indexed":true,"internalType":"address","name":"asset","type":"address"},{"indexed":false,"internalType":"uint8","name":"underlyingAssetDecimals","type":"uint8"},{"indexed":false,"internalType":"string","name":"underlyingAssetSymbol","type":"string"},{"indexed":false,"internalType":"uint256","name":"supplyCap","type":"uint256"},{"indexed":false,"internalType":"uint256","name":"borrowCap","type":"uint256"},{"indexed":false,"internalType":"uint256","name":"baseLTV","type":"uint256"},{"indexed":false,"internalType":"uint256","name":"liquidationThreshold","type":"uint256"},{"indexed":false,"internalType":"uint256","name":"liquidationBonus","type":"uint256"},{"indexed":false,"internalType":"uint256","name":"borrowFactor","type":"uint256"},{"indexed":false,"internalType":"address","name":"defaultInterestRateStrategyAddress","type":"address"},{"indexed":false,"internalType":"bool","name":"borrowingEnabled","type":"bool"},{"indexed":false,"internalType":"uint256","name":"VMEXReserveFactor","type":"uint256"}],"name":"AssetDataSet","type":"event"},{"anonymous":false,"inputs":[{"indexed":true,"internalType":"address","name":"asset","type":"address"},{"indexed":false,"internalType":"bool","name":"borrowingEnabled","type":"bool"}],"name":"BorrowingEnabledChanged","type":"event"},{"anonymous":false,"inputs":[{"indexed":true,"internalType":"address","name":"asset","type":"address"},{"indexed":false,"internalType":"uint256","name":"baseLTV","type":"uint256"},{"indexed":false,"internalType":"uint256","name":"liquidationThreshold","type":"uint256"},{"indexed":false,"internalType":"uint256","name":"liquidationBonus","type":"uint256"},{"indexed":false,"internalType":"uint256","name":"supplyCap","type":"uint256"},{"indexed":false,"internalType":"uint256","name":"borrowCap","type":"uint256"},{"indexed":false,"internalType":"uint256","name":"borrowFactor","type":"uint256"}],"name":"ConfiguredAssetMapping","type":"event"},{"anonymous":false,"inputs":[{"indexed":false,"internalType":"uint8","name":"version","type":"uint8"}],"name":"Initialized","type":"event"},{"anonymous":false,"inputs":[{"indexed":true,"internalType":"address","name":"asset","type":"address"},{"indexed":false,"internalType":"uint256","name":"factor","type":"uint256"}],"name":"VMEXReserveFactorChanged","type":"event"},{"inputs":[{"components":[{"internalType":"address","name":"asset","type":"address"},{"internalType":"address","name":"defaultInterestRateStrategyAddress","type":"address"},{"internalType":"uint128","name":"supplyCap","type":"uint128"},{"internalType":"uint128","name":"borrowCap","type":"uint128"},{"internalType":"uint64","name":"baseLTV","type":"uint64"},{"internalType":"uint64","name":"liquidationThreshold","type":"uint64"},{"internalType":"uint64","name":"liquidationBonus","type":"uint64"},{"internalType":"uint64","name":"borrowFactor","type":"uint64"},{"internalType":"bool","name":"borrowingEnabled","type":"bool"},{"internalType":"uint8","name":"assetType","type":"uint8"},{"internalType":"uint64","name":"VMEXReserveFactor","type":"uint64"}],"internalType":"struct IAssetMappings.AddAssetMappingInput[]","name":"input","type":"tuple[]"}],"name":"addAssetMapping","outputs":[],"stateMutability":"nonpayable","type":"function"},{"inputs":[],"name":"approvedAssetsHead","outputs":[{"internalType":"address","name":"","type":"address"}],"stateMutability":"view","type":"function"},{"inputs":[],"name":"approvedAssetsTail","outputs":[{"internalType":"address","name":"","type":"address"}],"stateMutability":"view","type":"function"},{"inputs":[{"internalType":"address","name":"asset","type":"address"},{"internalType":"uint64","name":"baseLTV","type":"uint64"},{"internalType":"uint64","name":"liquidationThreshold","type":"uint64"},{"internalType":"uint64","name":"liquidationBonus","type":"uint64"},{"internalType":"uint128","name":"supplyCap","type":"uint128"},{"internalType":"uint128","name":"borrowCap","type":"uint128"},{"internalType":"uint64","name":"borrowFactor","type":"uint64"}],"name":"configureAssetMapping","outputs":[],"stateMutability":"nonpayable","type":"function"},{"inputs":[],"name":"getAllApprovedTokens","outputs":[{"internalType":"address[]","name":"tokens","type":"address[]"}],"stateMutability":"view","type":"function"},{"inputs":[{"internalType":"address","name":"asset","type":"address"}],"name":"getAssetAllowed","outputs":[{"internalType":"bool","name":"","type":"bool"}],"stateMutability":"view","type":"function"},{"inputs":[{"internalType":"address","name":"asset","type":"address"}],"name":"getAssetBorrowable","outputs":[{"internalType":"bool","name":"","type":"bool"}],"stateMutability":"view","type":"function"},{"inputs":[{"internalType":"address","name":"asset","type":"address"}],"name":"getAssetCollateralizable","outputs":[{"internalType":"bool","name":"","type":"bool"}],"stateMutability":"view","type":"function"},{"inputs":[{"internalType":"address","name":"asset","type":"address"}],"name":"getAssetMapping","outputs":[{"components":[{"internalType":"uint128","name":"supplyCap","type":"uint128"},{"internalType":"uint128","name":"borrowCap","type":"uint128"},{"internalType":"uint64","name":"baseLTV","type":"uint64"},{"internalType":"uint64","name":"liquidationThreshold","type":"uint64"},{"internalType":"uint64","name":"liquidationBonus","type":"uint64"},{"internalType":"uint64","name":"borrowFactor","type":"uint64"},{"internalType":"bool","name":"borrowingEnabled","type":"bool"},{"internalType":"bool","name":"isAllowed","type":"bool"},{"internalType":"bool","name":"exists","type":"bool"},{"internalType":"uint8","name":"assetType","type":"uint8"},{"internalType":"uint64","name":"VMEXReserveFactor","type":"uint64"},{"internalType":"address","name":"defaultInterestRateStrategyAddress","type":"address"},{"internalType":"address","name":"nextApprovedAsset","type":"address"}],"internalType":"struct DataTypes.AssetData","name":"","type":"tuple"}],"stateMutability":"view","type":"function"},{"inputs":[{"internalType":"address","name":"asset","type":"address"}],"name":"getAssetType","outputs":[{"internalType":"enum DataTypes.ReserveAssetType","name":"","type":"uint8"}],"stateMutability":"view","type":"function"},{"inputs":[{"internalType":"address","name":"asset","type":"address"}],"name":"getBeethovenMetadata","outputs":[{"components":[{"internalType":"uint8","name":"_typeOfPool","type":"uint8"},{"internalType":"bool","name":"_legacy","type":"bool"},{"internalType":"bool","name":"_exists","type":"bool"}],"internalType":"struct DataTypes.BeethovenMetadata","name":"","type":"tuple"}],"stateMutability":"view","type":"function"},{"inputs":[{"internalType":"address","name":"asset","type":"address"}],"name":"getBorrowCap","outputs":[{"internalType":"uint256","name":"","type":"uint256"}],"stateMutability":"view","type":"function"},{"inputs":[{"internalType":"address","name":"asset","type":"address"}],"name":"getBorrowFactor","outputs":[{"internalType":"uint256","name":"","type":"uint256"}],"stateMutability":"view","type":"function"},{"inputs":[{"internalType":"address","name":"asset","type":"address"}],"name":"getCurveMetadata","outputs":[{"components":[{"internalType":"enum ICurvePool.CurveReentrancyType","name":"_reentrancyType","type":"uint8"},{"internalType":"uint8","name":"_poolSize","type":"uint8"},{"internalType":"address","name":"_curvePool","type":"address"}],"internalType":"struct DataTypes.CurveMetadata","name":"","type":"tuple"}],"stateMutability":"view","type":"function"},{"inputs":[{"internalType":"address","name":"asset","type":"address"}],"name":"getDecimals","outputs":[{"internalType":"uint256","name":"","type":"uint256"}],"stateMutability":"view","type":"function"},{"inputs":[{"internalType":"address","name":"asset","type":"address"}],"name":"getDefaultCollateralParams","outputs":[{"internalType":"uint64","name":"","type":"uint64"},{"internalType":"uint64","name":"","type":"uint64"},{"internalType":"uint64","name":"","type":"uint64"},{"internalType":"uint64","name":"","type":"uint64"}],"stateMutability":"view","type":"function"},{"inputs":[{"internalType":"address","name":"asset","type":"address"}],"name":"getDefaultInterestRateStrategyAddress","outputs":[{"internalType":"address","name":"","type":"address"}],"stateMutability":"view","type":"function"},{"inputs":[{"internalType":"address","name":"asset","type":"address"},{"internalType":"uint64","name":"trancheId","type":"uint64"}],"name":"getInterestRateStrategyAddress","outputs":[{"internalType":"address","name":"","type":"address"}],"stateMutability":"view","type":"function"},{"inputs":[],"name":"getNumApprovedTokens","outputs":[{"internalType":"uint256","name":"","type":"uint256"}],"stateMutability":"view","type":"function"},{"inputs":[{"internalType":"address","name":"asset","type":"address"},{"internalType":"uint64","name":"trancheId","type":"uint64"}],"name":"getParams","outputs":[{"internalType":"uint256","name":"baseLTV","type":"uint256"},{"internalType":"uint256","name":"liquidationThreshold","type":"uint256"},{"internalType":"uint256","name":"liquidationBonus","type":"uint256"},{"internalType":"uint256","name":"underlyingAssetDecimals","type":"uint256"},{"internalType":"uint256","name":"borrowFactor","type":"uint256"}],"stateMutability":"view","type":"function"},{"inputs":[{"internalType":"address","name":"asset","type":"address"}],"name":"getSupplyCap","outputs":[{"internalType":"uint256","name":"","type":"uint256"}],"stateMutability":"view","type":"function"},{"inputs":[{"internalType":"address","name":"asset","type":"address"}],"name":"getVMEXReserveFactor","outputs":[{"internalType":"uint256","name":"","type":"uint256"}],"stateMutability":"view","type":"function"},{"inputs":[{"internalType":"contract ILendingPoolAddressesProvider","name":"provider","type":"address"}],"name":"initialize","outputs":[],"stateMutability":"nonpayable","type":"function"},{"inputs":[{"internalType":"address","name":"asset","type":"address"}],"name":"isAssetInMappings","outputs":[{"internalType":"bool","name":"","type":"bool"}],"stateMutability":"view","type":"function"},{"inputs":[{"internalType":"address","name":"asset","type":"address"},{"internalType":"bool","name":"isAllowed","type":"bool"}],"name":"setAssetAllowed","outputs":[],"stateMutability":"nonpayable","type":"function"},{"inputs":[{"internalType":"address","name":"asset","type":"address"},{"internalType":"enum DataTypes.ReserveAssetType","name":"assetType","type":"uint8"}],"name":"setAssetType","outputs":[],"stateMutability":"nonpayable","type":"function"},{"inputs":[{"internalType":"address[]","name":"assets","type":"address[]"},{"components":[{"internalType":"uint8","name":"_typeOfPool","type":"uint8"},{"internalType":"bool","name":"_legacy","type":"bool"},{"internalType":"bool","name":"_exists","type":"bool"}],"internalType":"struct DataTypes.BeethovenMetadata[]","name":"vars","type":"tuple[]"}],"name":"setBeethovenMetadata","outputs":[],"stateMutability":"nonpayable","type":"function"},{"inputs":[{"internalType":"address","name":"asset","type":"address"},{"internalType":"bool","name":"borrowingEnabled","type":"bool"}],"name":"setBorrowingEnabled","outputs":[],"stateMutability":"nonpayable","type":"function"},{"inputs":[{"internalType":"address[]","name":"assets","type":"address[]"},{"components":[{"internalType":"enum ICurvePool.CurveReentrancyType","name":"_reentrancyType","type":"uint8"},{"internalType":"uint8","name":"_poolSize","type":"uint8"},{"internalType":"address","name":"_curvePool","type":"address"}],"internalType":"struct DataTypes.CurveMetadata[]","name":"vars","type":"tuple[]"}],"name":"setCurveMetadata","outputs":[],"stateMutability":"nonpayable","type":"function"},{"inputs":[{"internalType":"address","name":"asset","type":"address"},{"internalType":"address","name":"strategy","type":"address"}],"name":"setInterestRateStrategyAddress","outputs":[],"stateMutability":"nonpayable","type":"function"},{"inputs":[{"internalType":"address","name":"asset","type":"address"},{"internalType":"uint256","name":"reserveFactor","type":"uint256"}],"name":"setVMEXReserveFactor","outputs":[],"stateMutability":"nonpayable","type":"function"}]
